dt31/__init__.py
dt31/assembler.py
dt31/cli.py
dt31/cpu.py
dt31/exceptions.py
dt31/formatter.py
dt31/instructions.py
dt31/operands.py
dt31/parser.py
dt31-0.11.0.dist-info/WHEEL
dt31-0.11.0.dist-info/entry_points.txt
dt31-0.11.0.dist-info/METADATA
dt31-0.11.0.dist-info/RECORD
