Metadata-Version: 2.3
Name: dt31
Version: 0.11.0
Summary: A toy computer in Python.
Keywords: emulator,assembly,computer,virtual-machine,instruction-set,toy-computer,cpu,interpreter
Author: Dan Turkel
Author-email: Dan Turkel <daturkel@gmail.com>
License: MIT License
Classifier: Development Status :: 4 - Beta
Classifier: Programming Language :: Python
Classifier: Programming Language :: Python :: 3
Classifier: Programming Language :: Python :: 3.10
Classifier: Programming Language :: Python :: 3.11
Classifier: Programming Language :: Python :: 3.12
Classifier: Programming Language :: Python :: 3.13
Classifier: Programming Language :: Python :: 3.14
Classifier: Topic :: Software Development :: Interpreters
Classifier: Typing :: Typed
Maintainer: Dan Turkel
Maintainer-email: Dan Turkel <daaturkel@gmail.com>
Requires-Python: >=3.10
